Gerdoo/__init__.py
Gerdoo/enums.py
Gerdoo/gerdoo.py
gerdoo-1.2.0.dist-info/licenses/LICENSE
gerdoo-1.2.0.dist-info/METADATA
gerdoo-1.2.0.dist-info/WHEEL
gerdoo-1.2.0.dist-info/top_level.txt
gerdoo-1.2.0.dist-info/RECORD
