Metadata-Version: 2.4
Name: Gerdoo
Version: 1.2.0
Summary: This unofficial library is built for using the Gerdoo search engine. You can use this tool to search the web, images, videos, news, and more. 🐍✨
Author: MohammadReza
Author-email: narnama.room@gmail.com
Project-URL: موتور جستجوی گردو 🌐, https://gerdoo.me/
Project-URL: صفحه من ❤️, https://apicode.pythonanywhere.com/
Classifier: Programming Language :: Python :: 3
Classifier: License :: OSI Approved :: MIT License
Classifier: Operating System :: OS Independent
Requires-Python: >=3.5
License-File: LICENSE
Requires-Dist: requests
Requires-Dist: beautifulsoup4
Dynamic: author
Dynamic: author-email
Dynamic: classifier
Dynamic: description
Dynamic: description-content-type
Dynamic: license-file
Dynamic: project-url
Dynamic: requires-dist
Dynamic: requires-python
Dynamic: summary
